esipy/__init__.py
esipy/app.py
esipy/cache.py
esipy/client.py
esipy/events.py
esipy/exceptions.py
esipy/security.py
esipy/utils.py
EsiPy-1.2.3.dist-info/LICENSE
EsiPy-1.2.3.dist-info/METADATA
EsiPy-1.2.3.dist-info/WHEEL
EsiPy-1.2.3.dist-info/top_level.txt
EsiPy-1.2.3.dist-info/RECORD
