Metadata-Version: 1.1
Name: EsiPy
Version: 1.2.3
Summary: Swagger Client for the ESI API for EVE Online
Home-page: https://github.com/Kyria/EsiPy
Author: Kyria
Author-email: anakhon@gmail.com
License: BSD 3-Clause License
Platform: UNKNOWN
Classifier: Development Status :: 5 - Production/Stable
Classifier: Intended Audience :: Developers
Classifier: Programming Language :: Python
Classifier: Programming Language :: Python :: 3.5
Classifier: Programming Language :: Python :: 3.6
Classifier: Programming Language :: Python :: 3.7
Classifier: Programming Language :: Python :: 3.8
Classifier: Programming Language :: Python :: Implementation :: CPython
